stevens/__init__.py
stevens-0.1.2.dist-info/LICENSE.txt
stevens-0.1.2.dist-info/METADATA
stevens-0.1.2.dist-info/WHEEL
stevens-0.1.2.dist-info/top_level.txt
stevens-0.1.2.dist-info/RECORD
