Metadata-Version: 2.1
Name: stevens
Version: 0.1.2
Summary: Residue Classes
Author-email: Johannes <johannes-programming@mailfence.com>, Johannes <johannes-computer@mailfence.com>
License: The MIT License (MIT)
Project-URL: Documentation, https://pypi.org/project/stevens
Project-URL: Download, https://pypi.org/project/stevens/#files
Project-URL: Source, https://github.com/johannes-computer/stevens
Classifier: License :: OSI Approved :: MIT License
Classifier: Programming Language :: Python
Classifier: Programming Language :: Python :: 3
Classifier: Programming Language :: Python :: 3 :: Only
Requires-Python: >=3.11
License-File: LICENSE.txt
Requires-Dist: scaevola >=1.0.0
